datasol.py
datasol-0.0.101.dist-info/License.txt
datasol-0.0.101.dist-info/METADATA
datasol-0.0.101.dist-info/WHEEL
datasol-0.0.101.dist-info/top_level.txt
datasol-0.0.101.dist-info/RECORD
