Metadata-Version: 2.1
Name: datasol
Version: 0.0.101
Summary: Anomaly Detetion
Home-page: https://github.com/maxmelichov/DATASOL-package
Author: Maxim Melichov
Author-email: maxme006@gmail.com
License: MIT
Classifier: Development Status :: 5 - Production/Stable
Classifier: License :: OSI Approved :: MIT License
Classifier: Programming Language :: Python :: 3.9
License-File: License.txt
Provides-Extra: dev
Requires-Dist: pytest (>=3.7) ; extra == 'dev'
